queupy/__init__.py
queupy/agent.py
queupy/lock.py
queupy/model.py
queupy/policy.py
queupy/priority.py
queupy/queue.py
queupy/utils.py
tests/__init__.py
tests/assets.py
tests/conftest.py
tests/test_queue.py
queupy-0.2.5.dist-info/METADATA
queupy-0.2.5.dist-info/WHEEL
queupy-0.2.5.dist-info/top_level.txt
queupy-0.2.5.dist-info/RECORD
