Metadata-Version: 2.1
Name: queupy
Version: 0.2.5
Summary: A queuing library based on Peewee
Home-page: https://github.com/EnzoTheBrown/queupy
Author: Enzo Lebrun
Author-email: enzo.the@gmail.com
Classifier: Programming Language :: Python :: 3
Classifier: License :: OSI Approved :: MIT License
Classifier: Operating System :: OS Independent
Classifier: Development Status :: 3 - Alpha
Classifier: Intended Audience :: Developers
Classifier: Topic :: Software Development :: Libraries :: Python Modules
Classifier: Topic :: Database
Requires-Python: >=3.6
Requires-Dist: peewee >=3.14.0
